[
    {
        "hobby": "Рисование",
        "id": 1
    },
    {
        "hobby": "Писательство",
        "id": 2
    },
    {
        "hobby": "Программирование",
        "id": 3
    },
    {
        "hobby": "Вышивание",
        "id": 4
    },
    {
        "hobby": "Увлекается скрапбукингом",
        "id": 5
    },
    {
        "hobby": "Танцы",
        "id": 6
    },
    {
        "hobby": "Интересуется светскими новостями",
        "id": 7
    },
    {
        "hobby": "Астрология",
        "id": 8
    },
    {
        "hobby": "Картография",
        "id": 9
    },
    {
        "hobby": "Биология",
        "id": 10
    },
    {
        "hobby": "Физика",
        "id": 11
    },
    {
        "hobby": "Математика",
        "id": 12
    },
    {
        "hobby": "Делать украшения из бисера",
        "id": 13
    },
    {
        "hobby": "Делать мозайки",
        "id": 14
    },
    {
        "hobby": "Бег",
        "id": 15
    },
    {
        "hobby": "Азартные игры",
        "id": 16
    },
    {
        "hobby": "Шутки шутить",
        "id": 17
    },
    {
        "hobby": "Изготовлять куклы",
        "id": 18
    },
    {
        "hobby": "Плетение корзин из любых веток",
        "id": 19
    },
    {
        "hobby": "Животноводство",
        "id": 20
    },
    {
        "hobby": "Выращивание растений",
        "id": 21
    },
    {
        "hobby": "Занимается ювелирством",
        "id": 22
    },
    {
        "hobby": "Коллекционирует монеты",
        "id": 23
    },
    {
        "hobby": "Коллекционирует сушеных насекомых",
        "id": 24
    },
    {
        "hobby": "Готовка",
        "id": 25
    },
    {
        "hobby": "Альпинизм",
        "id": 26
    },
    {
        "hobby": "Тенис",
        "id": 27
    },
    {
        "hobby": "Баскетбол",
        "id": 28
    },
    {
        "hobby": "Волейбол",
        "id": 29
    },
    {
        "hobby": "Верховая езда",
        "id": 30
    },
    {
        "hobby": "Стрельба из лука",
        "id": 31
    },
    {
        "hobby": "Стрелять из оружия",
        "id": 32
    },
    {
        "hobby": "Увлекается иностранными языками",
        "id": 33
    },
    {
        "hobby": "Разрабатывание сайтов",
        "id": 34
    },
    {
        "hobby": "Выращивание кристаллов",
        "id": 35
    },
    {
        "hobby": "Лепит горшки и посуду из глины",
        "id": 36
    },
    {
        "hobby": "Разводить животных",
        "id": 37
    },
    {
        "hobby": "Разыгрывать всех подряд",
        "id": 38
    },
    {
        "hobby": "Плаванье",
        "id": 39
    },
    {
        "hobby": "Спорт",
        "id": 40
    },
    {
        "hobby": "Дрочка",
        "id": 41
    },
    {
        "hobby": "Автомобили Ароматерапия",
        "id": 42
    },
    {
        "hobby": "Астрономия",
        "id": 43
    },
    {
        "hobby": "Аэробика",
        "id": 44
    },
    {
        "hobby": "Аэрография",
        "id": 45
    },
    {
        "hobby": "Бадминтон",
        "id": 46
    },
    {
        "hobby": "Батик",
        "id": 47
    },
    {
        "hobby": "Батут",
        "id": 48
    },
    {
        "hobby": " Бильярд",
        "id": 49
    },
    {
        "hobby": "Блоггерство",
        "id": 50
    },
    {
        "hobby": "Бодиарт",
        "id": 51
    },
    {
        "hobby": "Боевые искусства",
        "id": 52
    },
    {
        "hobby": "Бонсай",
        "id": 53
    },
    {
        "hobby": "Боулинг",
        "id": 54
    },
    {
        "hobby": "Велосипед",
        "id": 55
    },
    {
        "hobby": "Видеомонтаж",
        "id": 56
    },
    {
        "hobby": "Выращивание кристаллов",
        "id": 57
    },
    {
        "hobby": "Выращивание растений и цветов",
        "id": 58
    },
    {
        "hobby": "Вязание",
        "id": 59
    },
    {
        "hobby": "Гербарий",
        "id": 60
    },
    {
        "hobby": "Головоломки",
        "id": 61
    },
    {
        "hobby": "Гольф",
        "id": 62
    },
    {
        "hobby": "Горные лыжи",
        "id": 63
    },
    {
        "hobby": "Граффити",
        "id": 64
    },
    {
        "hobby": "Дайвинг",
        "id": 65
    },
    {
        "hobby": "Дартс",
        "id": 66
    },
    {
        "hobby": "Декупаж",
        "id": 67
    },
    {
        "hobby": "Дерево (выжигание и резьба)",
        "id": 68
    },
    {
        "hobby": "Диггерство",
        "id": 69
    },
    {
        "hobby": "Дизайн интерьера",
        "id": 70
    },
    {
        "hobby": "Дизайн одежды",
        "id": 71
    },
    {
        "hobby": "Животные (разведение и уход)",
        "id": 72
    },
    {
        "hobby": "Жонглирование",
        "id": 73
    },
    {
        "hobby": "Зентангл",
        "id": 74
    },
    {
        "hobby": "Игра на музыкальных инструментах",
        "id": 75
    },
    {
        "hobby": "Игрушки и куклы",
        "id": 76
    },
    {
        "hobby": "Игры на компьютерах и приставках",
        "id": 77
    },
    {
        "hobby": "Изделия из металла и кузнечное дело",
        "id": 78
    },
    {
        "hobby": "Изучение новых компьютерных программ",
        "id": 79
    },
    {
        "hobby": "Икебана",
        "id": 80
    },
    {
        "hobby": "Иностранные языки",
        "id": 81
    },
    {
        "hobby": "Йога",
        "id": 82
    },
    {
        "hobby": "Исторические реконструкции",
        "id": 83
    },
    {
        "hobby": "Кайтинг",
        "id": 84
    },
    {
        "hobby": "Каллиграфия",
        "id": 85
    },
    {
        "hobby": "Карвинг",
        "id": 86
    },
    {
        "hobby": "Картинг и квадроциклы",
        "id": 87
    },
    {
        "hobby": "Квест-комнаты",
        "id": 88
    },
    {
        "hobby": "Кладоискательство и археология",
        "id": 89
    },
    {
        "hobby": "Клубный отдых",
        "id": 90
    },
    {
        "hobby": "Коллекционирование",
        "id": 91
    },
    {
        "hobby": "Компьютерная графика",
        "id": 92
    },
    {
        "hobby": "Концерты (посещение)",
        "id": 93
    },
    {
        "hobby": "Коньки и ролики",
        "id": 94
    },
    {
        "hobby": "Косплей",
        "id": 95
    },
    {
        "hobby": "Кроссворды (составление и разгадывание)",
        "id": 96
    },
    {
        "hobby": "Кулинария",
        "id": 97
    },
    {
        "hobby": "Лазертаг",
        "id": 98
    },
    {
        "hobby": "Лепка",
        "id": 99
    },
    {
        "hobby": "Лошади (верховая езда/уход)",
        "id": 100
    },
    {
        "hobby": "Лыжи",
        "id": 101
    },
    {
        "hobby": "Массаж",
        "id": 102
    },
    {
        "hobby": "Моделирование",
        "id": 103
    },
    {
        "hobby": "Музеи и выставки",
        "id": 104
    },
    {
        "hobby": "Музыка (написание ремиксы)",
        "id": 105
    },
    {
        "hobby": "Мыловарение",
        "id": 106
    },
    {
        "hobby": "Настольные игры",
        "id": 107
    },
    {
        "hobby": "Оригами",
        "id": 108
    },
    {
        "hobby": "Открытки (изготовление своими руками/обмен (посткроссинг))",
        "id": 109
    },
    {
        "hobby": "Охота",
        "id": 110
    },
    {
        "hobby": "Пазлы",
        "id": 111
    },
    {
        "hobby": "Парашютный спорт",
        "id": 112
    },
    {
        "hobby": "Паркур",
        "id": 113
    },
    {
        "hobby": "Пейнтбол",
        "id": 114
    },
    {
        "hobby": "Пение и караоке",
        "id": 115
    },
    {
        "hobby": "Переписка по обычной почте",
        "id": 116
    },
    {
        "hobby": "Пикап",
        "id": 117
    },
    {
        "hobby": "Пилатес",
        "id": 118
    },
    {
        "hobby": "Писательская деятельность и журналистика",
        "id": 119
    },
    {
        "hobby": "Плавание",
        "id": 120
    },
    {
        "hobby": "Плетение",
        "id": 121
    },
    {
        "hobby": "Получение научных званий и степеней",
        "id": 122
    },
    {
        "hobby": "Предпринимательство",
        "id": 123
    },
    {
        "hobby": "Программирование",
        "id": 124
    },
    {
        "hobby": "Психология и тренинги",
        "id": 125
    },
    {
        "hobby": "Путешествия",
        "id": 126
    },
    {
        "hobby": "Пчеловодство",
        "id": 127
    },
    {
        "hobby": "Радиовещание",
        "id": 128
    },
    {
        "hobby": "Разработка сайтов",
        "id": 129
    },
    {
        "hobby": "Рисование",
        "id": 130
    },
    {
        "hobby": "",
        "id": 131
    },
    {
        "hobby": "Робототехника",
        "id": 132
    },
    {
        "hobby": "Рукоделия из кожи (одежда аксессуары)",
        "id": 133
    },
    {
        "hobby": "Рыбалка",
        "id": 134
    },
    {
        "hobby": "Самодельные вещи: одежда обувь аксессуары",
        "id": 135
    },
    {
        "hobby": "Серфинг",
        "id": 136
    },
    {
        "hobby": "Силовые тренировки",
        "id": 137
    },
    {
        "hobby": "Скейтборд",
        "id": 138
    },
    {
        "hobby": "Скрапбукинг (фотоальбомы своими руками)",
        "id": 139
    },
    {
        "hobby": "Сноуборд",
        "id": 140
    },
    {
        "hobby": "Собирание грибов и ягод",
        "id": 141
    },
    {
        "hobby": "Спорт-фанат",
        "id": 142
    },
    {
        "hobby": "Стекло (изготовление украшений и предметов интерьера)",
        "id": 143
    },
    {
        "hobby": "Страйкбол",
        "id": 144
    },
    {
        "hobby": "Стрельба",
        "id": 145
    },
    {
        "hobby": "Танцы и балет",
        "id": 146
    },
    {
        "hobby": "Татуировки и пирсинг",
        "id": 147
    },
    {
        "hobby": "Театр (театральный кружок)",
        "id": 148
    },
    {
        "hobby": "Теннис",
        "id": 149
    },
    {
        "hobby": "Файер-шоу",
        "id": 150
    },
    {
        "hobby": "Фейерверки",
        "id": 151
    },
    {
        "hobby": "Фокусы",
        "id": 152
    },
    {
        "hobby": "Фотография и фотокниги",
        "id": 153
    },
    {
        "hobby": "Футбол",
        "id": 154
    },
    {
        "hobby": "Шитье и вышивание",
        "id": 155
    },
    {
        "hobby": "Чтение книг",
        "id": 156
    },
    {
        "hobby": "Наблюдение за птицами",
        "id": 157
    },
    {
        "hobby": "Гадание на картах",
        "id": 158
    },
    {
        "hobby": "Ребусы",
        "id": 159
    },
    {
        "hobby": "Мода",
        "id": 160
    },
    {
        "hobby": "Флористика",
        "id": 161
    },
    {
        "hobby": "Каратэ",
        "id": 162
    },
    {
        "hobby": "Теквандо",
        "id": 163
    },
    {
        "hobby": "Дзюдо",
        "id": 164
    },
    {
        "hobby": "Бодибилдинг",
        "id": 165
    },
    {
        "hobby": "Фотография",
        "id": 166
    },
    {
        "hobby": "Скалолазание",
        "id": 167
    },
    {
        "hobby": "Парусный спорт",
        "id": 168
    },
    {
        "hobby": "Викторины",
        "id": 169
    },
    {
        "hobby": "Сыроварение",
        "id": 170
    },
    {
        "hobby": "Домохозяйство",
        "id": 171
    },
    {
        "hobby": "Космология",
        "id": 172
    },
    {
        "hobby": "Косметология",
        "id": 173
    },
    {
        "hobby": "Сбор грибов",
        "id": 174
    },
    {
        "hobby": "Садоводство",
        "id": 175
    },
    {
        "hobby": "Музыка",
        "id": 176
    },
    {
        "hobby": "Кунг-Фу",
        "id": 177
    },
    {
        "hobby": "Занимается изучением медицины",
        "id": 178
    },
    {
        "hobby": "Изучение почвоведения",
        "id": 179
    },
    {
        "hobby": "Изучение психологии",
        "id": 180
    },
    {
        "hobby": "Оброботка металла",
        "id": 181
    },
    {
        "hobby": "Битбокс",
        "id": 182
    }
]